{"name":"Validation of language change to \"Mandarin\"","id":"change-page-language;validation-of-language-change-to-\"mandarin\"","testSteps":[{"number":1,"description":"Given the user is on the page","duration":8182,"startTime":"2023-09-28T08:37:36.183-05:00[America/Bogota]","screenshots":[{"screenshot":"124dc289bfc4a337f5b15a917581227ef1f19499be75b31ea4a6fb040d433b2f.png","timeStamp":1695908264365}],"result":"SUCCESS","precondition":false,"level":0,"children":[{"number":2,"description":"Team15 opens the https://www.booking.com/","duration":8147,"startTime":"2023-09-28T08:37:36.192-05:00[America/Bogota]","screenshots":[{"screenshot":"124dc289bfc4a337f5b15a917581227ef1f19499be75b31ea4a6fb040d433b2f.png","timeStamp":1695908264339}],"result":"SUCCESS","precondition":false,"level":1}]},{"number":3,"description":"When the user changes the language to Mandarin","duration":9040,"startTime":"2023-09-28T08:37:44.366-05:00[America/Bogota]","screenshots":[{"screenshot":"124dc289bfc4a337f5b15a917581227ef1f19499be75b31ea4a6fb040d433b2f.png","timeStamp":1695908264380}],"exception":{"errorType":"net.thucydides.core.webdriver.exceptions.ElementShouldBePresentException","message":"Expected condition failed: waiting for By.xpath: //button [@data-testid \u003d \u0027selection-item\u0027]//span [contains(text(),\u0027简体中文\u0027)] to be present (tried for 5 second(s) with 100 milliseconds interval)\nBuild info: version: \u00273.141.59\u0027, revision: \u0027e82be7d358\u0027, time: \u00272018-11-14T08:17:03\u0027\nSystem info: host: \u0027DESKTOP-AM3VRUH\u0027, ip: \u0027172.18.1.223\u0027, os.name: \u0027Windows 10\u0027, os.arch: \u0027amd64\u0027, os.version: \u002710.0\u0027, java.version: \u00271.8.0_202\u0027\nDriver info: driver.version: unknown","stackTrace":[{"declaringClass":"com.co.booking.task.ChangeLanguageMandarin","methodName":"performAs","fileName":"ChangeLanguageMandarin.java","lineNumber":15},{"declaringClass":"com.co.booking.steptsdefinitions.changeLanguagesStepDefinition","methodName":"theUserChangesTheLanguageToMandarin","fileName":"changeLanguagesStepDefinition.java","lineNumber":138},{"declaringClass":"io.cucumber.java.Invoker","methodName":"doInvoke","fileName":"Invoker.java","lineNumber":66},{"declaringClass":"io.cucumber.java.Invoker","methodName":"invoke","fileName":"Invoker.java","lineNumber":24},{"declaringClass":"io.cucumber.java.AbstractGlueDefinition","methodName":"invokeMethod","fileName":"AbstractGlueDefinition.java","lineNumber":47},{"declaringClass":"io.cucumber.java.JavaStepDefinition","methodName":"execute","fileName":"JavaStepDefinition.java","lineNumber":29},{"declaringClass":"io.cucumber.core.runner.CoreStepDefinition","methodName":"execute","fileName":"CoreStepDefinition.java","lineNumber":66},{"declaringClass":"io.cucumber.core.runner.PickleStepDefinitionMatch","methodName":"runStep","fileName":"PickleStepDefinitionMatch.java","lineNumber":63},{"declaringClass":"io.cucumber.core.runner.TestStep","methodName":"executeStep","fileName":"TestStep.java","lineNumber":92},{"declaringClass":"io.cucumber.core.runner.TestStep","methodName":"run","fileName":"TestStep.java","lineNumber":64},{"declaringClass":"io.cucumber.core.runner.PickleStepTestStep","methodName":"run","fileName":"PickleStepTestStep.java","lineNumber":51},{"declaringClass":"io.cucumber.core.runner.TestCase","methodName":"run","fileName":"TestCase.java","lineNumber":104},{"declaringClass":"io.cucumber.core.runner.Runner","methodName":"runPickle","fileName":"Runner.java","lineNumber":73},{"declaringClass":"io.cucumber.junit.FeatureRunner","methodName":"runChild","fileName":"FeatureRunner.java","lineNumber":135},{"declaringClass":"io.cucumber.junit.FeatureRunner","methodName":"runChild","fileName":"FeatureRunner.java","lineNumber":27},{"declaringClass":"io.cucumber.junit.CucumberSerenityRunner","methodName":"runChild","fileName":"CucumberSerenityRunner.java","lineNumber":258},{"declaringClass":"io.cucumber.junit.CucumberSerenityRunner","methodName":"runChild","fileName":"CucumberSerenityRunner.java","lineNumber":57},{"declaringClass":"worker.org.gradle.process.internal.worker.GradleWorkerMain","methodName":"run","fileName":"GradleWorkerMain.java","lineNumber":69},{"declaringClass":"worker.org.gradle.process.internal.worker.GradleWorkerMain","methodName":"main","fileName":"GradleWorkerMain.java","lineNumber":74}],"rootCause":{"errorType":"org.openqa.selenium.TimeoutException","message":"Expected condition failed: waiting for By.xpath: //button [@data-testid \u003d \u0027selection-item\u0027]//span [contains(text(),\u0027简体中文\u0027)] to be present (tried for 5 second(s) with 100 milliseconds interval)\nBuild info: version: \u00273.141.59\u0027, revision: \u0027e82be7d358\u0027, time: \u00272018-11-14T08:17:03\u0027\nSystem info: host: \u0027DESKTOP-AM3VRUH\u0027, ip: \u0027172.18.1.223\u0027, os.name: \u0027Windows 10\u0027, os.arch: \u0027amd64\u0027, os.version: \u002710.0\u0027, java.version: \u00271.8.0_202\u0027\nDriver info: driver.version: unknown","stackTrace":[{"declaringClass":"com.co.booking.task.ChangeLanguageMandarin","methodName":"performAs","fileName":"ChangeLanguageMandarin.java","lineNumber":15},{"declaringClass":"com.co.booking.steptsdefinitions.changeLanguagesStepDefinition","methodName":"theUserChangesTheLanguageToMandarin","fileName":"changeLanguagesStepDefinition.java","lineNumber":138},{"declaringClass":"io.cucumber.java.Invoker","methodName":"doInvoke","fileName":"Invoker.java","lineNumber":66},{"declaringClass":"io.cucumber.java.Invoker","methodName":"invoke","fileName":"Invoker.java","lineNumber":24},{"declaringClass":"io.cucumber.java.AbstractGlueDefinition","methodName":"invokeMethod","fileName":"AbstractGlueDefinition.java","lineNumber":47},{"declaringClass":"io.cucumber.java.JavaStepDefinition","methodName":"execute","fileName":"JavaStepDefinition.java","lineNumber":29},{"declaringClass":"io.cucumber.core.runner.CoreStepDefinition","methodName":"execute","fileName":"CoreStepDefinition.java","lineNumber":66},{"declaringClass":"io.cucumber.core.runner.PickleStepDefinitionMatch","methodName":"runStep","fileName":"PickleStepDefinitionMatch.java","lineNumber":63},{"declaringClass":"io.cucumber.core.runner.TestStep","methodName":"executeStep","fileName":"TestStep.java","lineNumber":92},{"declaringClass":"io.cucumber.core.runner.TestStep","methodName":"run","fileName":"TestStep.java","lineNumber":64},{"declaringClass":"io.cucumber.core.runner.PickleStepTestStep","methodName":"run","fileName":"PickleStepTestStep.java","lineNumber":51},{"declaringClass":"io.cucumber.core.runner.TestCase","methodName":"run","fileName":"TestCase.java","lineNumber":104},{"declaringClass":"io.cucumber.core.runner.Runner","methodName":"runPickle","fileName":"Runner.java","lineNumber":73},{"declaringClass":"io.cucumber.junit.FeatureRunner","methodName":"runChild","fileName":"FeatureRunner.java","lineNumber":135},{"declaringClass":"io.cucumber.junit.FeatureRunner","methodName":"runChild","fileName":"FeatureRunner.java","lineNumber":27},{"declaringClass":"io.cucumber.junit.CucumberSerenityRunner","methodName":"runChild","fileName":"CucumberSerenityRunner.java","lineNumber":258},{"declaringClass":"io.cucumber.junit.CucumberSerenityRunner","methodName":"runChild","fileName":"CucumberSerenityRunner.java","lineNumber":57},{"declaringClass":"worker.org.gradle.process.internal.worker.GradleWorkerMain","methodName":"run","fileName":"GradleWorkerMain.java","lineNumber":69},{"declaringClass":"worker.org.gradle.process.internal.worker.GradleWorkerMain","methodName":"main","fileName":"GradleWorkerMain.java","lineNumber":74}]}},"result":"FAILURE","precondition":false,"level":0,"children":[{"number":4,"description":"Team15 change language mandarin","duration":8998,"startTime":"2023-09-28T08:37:44.396-05:00[America/Bogota]","screenshots":[{"screenshot":"2ecc0160e763d135d693c6f6507558f546af95a2ad8624f7b652f7e4a95d9559.png","timeStamp":1695908264853}],"exception":{"errorType":"net.thucydides.core.webdriver.exceptions.ElementShouldBePresentException","message":"Expected condition failed: waiting for By.xpath: //button [@data-testid \u003d \u0027selection-item\u0027]//span [contains(text(),\u0027简体中文\u0027)] to be present (tried for 5 second(s) with 100 milliseconds interval)\nBuild info: version: \u00273.141.59\u0027, revision: \u0027e82be7d358\u0027, time: \u00272018-11-14T08:17:03\u0027\nSystem info: host: \u0027DESKTOP-AM3VRUH\u0027, ip: \u0027172.18.1.223\u0027, os.name: \u0027Windows 10\u0027, os.arch: \u0027amd64\u0027, os.version: \u002710.0\u0027, java.version: \u00271.8.0_202\u0027\nDriver info: driver.version: unknown","stackTrace":[{"declaringClass":"com.co.booking.task.ChangeLanguageMandarin","methodName":"performAs","fileName":"ChangeLanguageMandarin.java","lineNumber":15},{"declaringClass":"com.co.booking.steptsdefinitions.changeLanguagesStepDefinition","methodName":"theUserChangesTheLanguageToMandarin","fileName":"changeLanguagesStepDefinition.java","lineNumber":138},{"declaringClass":"io.cucumber.java.Invoker","methodName":"doInvoke","fileName":"Invoker.java","lineNumber":66},{"declaringClass":"io.cucumber.java.Invoker","methodName":"invoke","fileName":"Invoker.java","lineNumber":24},{"declaringClass":"io.cucumber.java.AbstractGlueDefinition","methodName":"invokeMethod","fileName":"AbstractGlueDefinition.java","lineNumber":47},{"declaringClass":"io.cucumber.java.JavaStepDefinition","methodName":"execute","fileName":"JavaStepDefinition.java","lineNumber":29},{"declaringClass":"io.cucumber.core.runner.CoreStepDefinition","methodName":"execute","fileName":"CoreStepDefinition.java","lineNumber":66},{"declaringClass":"io.cucumber.core.runner.PickleStepDefinitionMatch","methodName":"runStep","fileName":"PickleStepDefinitionMatch.java","lineNumber":63},{"declaringClass":"io.cucumber.core.runner.TestStep","methodName":"executeStep","fileName":"TestStep.java","lineNumber":92},{"declaringClass":"io.cucumber.core.runner.TestStep","methodName":"run","fileName":"TestStep.java","lineNumber":64},{"declaringClass":"io.cucumber.core.runner.PickleStepTestStep","methodName":"run","fileName":"PickleStepTestStep.java","lineNumber":51},{"declaringClass":"io.cucumber.core.runner.TestCase","methodName":"run","fileName":"TestCase.java","lineNumber":104},{"declaringClass":"io.cucumber.core.runner.Runner","methodName":"runPickle","fileName":"Runner.java","lineNumber":73},{"declaringClass":"io.cucumber.junit.FeatureRunner","methodName":"runChild","fileName":"FeatureRunner.java","lineNumber":135},{"declaringClass":"io.cucumber.junit.FeatureRunner","methodName":"runChild","fileName":"FeatureRunner.java","lineNumber":27},{"declaringClass":"io.cucumber.junit.CucumberSerenityRunner","methodName":"runChild","fileName":"CucumberSerenityRunner.java","lineNumber":258},{"declaringClass":"io.cucumber.junit.CucumberSerenityRunner","methodName":"runChild","fileName":"CucumberSerenityRunner.java","lineNumber":57},{"declaringClass":"worker.org.gradle.process.internal.worker.GradleWorkerMain","methodName":"run","fileName":"GradleWorkerMain.java","lineNumber":69},{"declaringClass":"worker.org.gradle.process.internal.worker.GradleWorkerMain","methodName":"main","fileName":"GradleWorkerMain.java","lineNumber":74}],"rootCause":{"errorType":"org.openqa.selenium.TimeoutException","message":"Expected condition failed: waiting for By.xpath: //button [@data-testid \u003d \u0027selection-item\u0027]//span [contains(text(),\u0027简体中文\u0027)] to be present (tried for 5 second(s) with 100 milliseconds interval)\nBuild info: version: \u00273.141.59\u0027, revision: \u0027e82be7d358\u0027, time: \u00272018-11-14T08:17:03\u0027\nSystem info: host: \u0027DESKTOP-AM3VRUH\u0027, ip: \u0027172.18.1.223\u0027, os.name: \u0027Windows 10\u0027, os.arch: \u0027amd64\u0027, os.version: \u002710.0\u0027, java.version: \u00271.8.0_202\u0027\nDriver info: driver.version: unknown","stackTrace":[{"declaringClass":"com.co.booking.task.ChangeLanguageMandarin","methodName":"performAs","fileName":"ChangeLanguageMandarin.java","lineNumber":15},{"declaringClass":"com.co.booking.steptsdefinitions.changeLanguagesStepDefinition","methodName":"theUserChangesTheLanguageToMandarin","fileName":"changeLanguagesStepDefinition.java","lineNumber":138},{"declaringClass":"io.cucumber.java.Invoker","methodName":"doInvoke","fileName":"Invoker.java","lineNumber":66},{"declaringClass":"io.cucumber.java.Invoker","methodName":"invoke","fileName":"Invoker.java","lineNumber":24},{"declaringClass":"io.cucumber.java.AbstractGlueDefinition","methodName":"invokeMethod","fileName":"AbstractGlueDefinition.java","lineNumber":47},{"declaringClass":"io.cucumber.java.JavaStepDefinition","methodName":"execute","fileName":"JavaStepDefinition.java","lineNumber":29},{"declaringClass":"io.cucumber.core.runner.CoreStepDefinition","methodName":"execute","fileName":"CoreStepDefinition.java","lineNumber":66},{"declaringClass":"io.cucumber.core.runner.PickleStepDefinitionMatch","methodName":"runStep","fileName":"PickleStepDefinitionMatch.java","lineNumber":63},{"declaringClass":"io.cucumber.core.runner.TestStep","methodName":"executeStep","fileName":"TestStep.java","lineNumber":92},{"declaringClass":"io.cucumber.core.runner.TestStep","methodName":"run","fileName":"TestStep.java","lineNumber":64},{"declaringClass":"io.cucumber.core.runner.PickleStepTestStep","methodName":"run","fileName":"PickleStepTestStep.java","lineNumber":51},{"declaringClass":"io.cucumber.core.runner.TestCase","methodName":"run","fileName":"TestCase.java","lineNumber":104},{"declaringClass":"io.cucumber.core.runner.Runner","methodName":"runPickle","fileName":"Runner.java","lineNumber":73},{"declaringClass":"io.cucumber.junit.FeatureRunner","methodName":"runChild","fileName":"FeatureRunner.java","lineNumber":135},{"declaringClass":"io.cucumber.junit.FeatureRunner","methodName":"runChild","fileName":"FeatureRunner.java","lineNumber":27},{"declaringClass":"io.cucumber.junit.CucumberSerenityRunner","methodName":"runChild","fileName":"CucumberSerenityRunner.java","lineNumber":258},{"declaringClass":"io.cucumber.junit.CucumberSerenityRunner","methodName":"runChild","fileName":"CucumberSerenityRunner.java","lineNumber":57},{"declaringClass":"worker.org.gradle.process.internal.worker.GradleWorkerMain","methodName":"run","fileName":"GradleWorkerMain.java","lineNumber":69},{"declaringClass":"worker.org.gradle.process.internal.worker.GradleWorkerMain","methodName":"main","fileName":"GradleWorkerMain.java","lineNumber":74}]}},"result":"FAILURE","precondition":false,"level":1,"children":[{"number":5,"description":"Team15 clicks on Clic para cerrar anuncio","duration":892,"startTime":"2023-09-28T08:37:44.859-05:00[America/Bogota]","screenshots":[{"screenshot":"2ecc0160e763d135d693c6f6507558f546af95a2ad8624f7b652f7e4a95d9559.png","timeStamp":1695908264873},{"screenshot":"963d0a74b60c4c677716ef5d876be9a219889ed0b036b28b59260931dc5a2989.png","timeStamp":1695908265751}],"result":"SUCCESS","precondition":false,"level":2},{"number":6,"description":"Team15 clicks on Selecciona tu idioma","duration":743,"startTime":"2023-09-28T08:37:45.753-05:00[America/Bogota]","screenshots":[{"screenshot":"963d0a74b60c4c677716ef5d876be9a219889ed0b036b28b59260931dc5a2989.png","timeStamp":1695908265766},{"screenshot":"9aed77a6b27a6974d2af1070a8be377928f34894ec6ad522900dcb86a95007e1.png","timeStamp":1695908266495}],"result":"SUCCESS","precondition":false,"level":2},{"number":7,"description":"Team15 clicks on 简体中文","duration":6885,"startTime":"2023-09-28T08:37:46.497-05:00[America/Bogota]","screenshots":[{"screenshot":"9aed77a6b27a6974d2af1070a8be377928f34894ec6ad522900dcb86a95007e1.png","timeStamp":1695908266513},{"screenshot":"87c47712c3d90e63c6791972921de5e6db9150d63471be760ebefad366eb4968.png","htmlSource":"pagesource6188709381642793206.html.txt","timeStamp":1695908273381}],"exception":{"errorType":"net.thucydides.core.webdriver.exceptions.ElementShouldBePresentException","message":"Expected condition failed: waiting for By.xpath: //button [@data-testid \u003d \u0027selection-item\u0027]//span [contains(text(),\u0027简体中文\u0027)] to be present (tried for 5 second(s) with 100 milliseconds interval)\nBuild info: version: \u00273.141.59\u0027, revision: \u0027e82be7d358\u0027, time: \u00272018-11-14T08:17:03\u0027\nSystem info: host: \u0027DESKTOP-AM3VRUH\u0027, ip: \u0027172.18.1.223\u0027, os.name: \u0027Windows 10\u0027, os.arch: \u0027amd64\u0027, os.version: \u002710.0\u0027, java.version: \u00271.8.0_202\u0027\nDriver info: driver.version: unknown","stackTrace":[{"declaringClass":"com.co.booking.task.ChangeLanguageMandarin","methodName":"performAs","fileName":"ChangeLanguageMandarin.java","lineNumber":15},{"declaringClass":"com.co.booking.steptsdefinitions.changeLanguagesStepDefinition","methodName":"theUserChangesTheLanguageToMandarin","fileName":"changeLanguagesStepDefinition.java","lineNumber":138},{"declaringClass":"io.cucumber.java.Invoker","methodName":"doInvoke","fileName":"Invoker.java","lineNumber":66},{"declaringClass":"io.cucumber.java.Invoker","methodName":"invoke","fileName":"Invoker.java","lineNumber":24},{"declaringClass":"io.cucumber.java.AbstractGlueDefinition","methodName":"invokeMethod","fileName":"AbstractGlueDefinition.java","lineNumber":47},{"declaringClass":"io.cucumber.java.JavaStepDefinition","methodName":"execute","fileName":"JavaStepDefinition.java","lineNumber":29},{"declaringClass":"io.cucumber.core.runner.CoreStepDefinition","methodName":"execute","fileName":"CoreStepDefinition.java","lineNumber":66},{"declaringClass":"io.cucumber.core.runner.PickleStepDefinitionMatch","methodName":"runStep","fileName":"PickleStepDefinitionMatch.java","lineNumber":63},{"declaringClass":"io.cucumber.core.runner.TestStep","methodName":"executeStep","fileName":"TestStep.java","lineNumber":92},{"declaringClass":"io.cucumber.core.runner.TestStep","methodName":"run","fileName":"TestStep.java","lineNumber":64},{"declaringClass":"io.cucumber.core.runner.PickleStepTestStep","methodName":"run","fileName":"PickleStepTestStep.java","lineNumber":51},{"declaringClass":"io.cucumber.core.runner.TestCase","methodName":"run","fileName":"TestCase.java","lineNumber":104},{"declaringClass":"io.cucumber.core.runner.Runner","methodName":"runPickle","fileName":"Runner.java","lineNumber":73},{"declaringClass":"io.cucumber.junit.FeatureRunner","methodName":"runChild","fileName":"FeatureRunner.java","lineNumber":135},{"declaringClass":"io.cucumber.junit.FeatureRunner","methodName":"runChild","fileName":"FeatureRunner.java","lineNumber":27},{"declaringClass":"io.cucumber.junit.CucumberSerenityRunner","methodName":"runChild","fileName":"CucumberSerenityRunner.java","lineNumber":258},{"declaringClass":"io.cucumber.junit.CucumberSerenityRunner","methodName":"runChild","fileName":"CucumberSerenityRunner.java","lineNumber":57},{"declaringClass":"worker.org.gradle.process.internal.worker.GradleWorkerMain","methodName":"run","fileName":"GradleWorkerMain.java","lineNumber":69},{"declaringClass":"worker.org.gradle.process.internal.worker.GradleWorkerMain","methodName":"main","fileName":"GradleWorkerMain.java","lineNumber":74}],"rootCause":{"errorType":"org.openqa.selenium.TimeoutException","message":"Expected condition failed: waiting for By.xpath: //button [@data-testid \u003d \u0027selection-item\u0027]//span [contains(text(),\u0027简体中文\u0027)] to be present (tried for 5 second(s) with 100 milliseconds interval)\nBuild info: version: \u00273.141.59\u0027, revision: \u0027e82be7d358\u0027, time: \u00272018-11-14T08:17:03\u0027\nSystem info: host: \u0027DESKTOP-AM3VRUH\u0027, ip: \u0027172.18.1.223\u0027, os.name: \u0027Windows 10\u0027, os.arch: \u0027amd64\u0027, os.version: \u002710.0\u0027, java.version: \u00271.8.0_202\u0027\nDriver info: driver.version: unknown","stackTrace":[{"declaringClass":"com.co.booking.task.ChangeLanguageMandarin","methodName":"performAs","fileName":"ChangeLanguageMandarin.java","lineNumber":15},{"declaringClass":"com.co.booking.steptsdefinitions.changeLanguagesStepDefinition","methodName":"theUserChangesTheLanguageToMandarin","fileName":"changeLanguagesStepDefinition.java","lineNumber":138},{"declaringClass":"io.cucumber.java.Invoker","methodName":"doInvoke","fileName":"Invoker.java","lineNumber":66},{"declaringClass":"io.cucumber.java.Invoker","methodName":"invoke","fileName":"Invoker.java","lineNumber":24},{"declaringClass":"io.cucumber.java.AbstractGlueDefinition","methodName":"invokeMethod","fileName":"AbstractGlueDefinition.java","lineNumber":47},{"declaringClass":"io.cucumber.java.JavaStepDefinition","methodName":"execute","fileName":"JavaStepDefinition.java","lineNumber":29},{"declaringClass":"io.cucumber.core.runner.CoreStepDefinition","methodName":"execute","fileName":"CoreStepDefinition.java","lineNumber":66},{"declaringClass":"io.cucumber.core.runner.PickleStepDefinitionMatch","methodName":"runStep","fileName":"PickleStepDefinitionMatch.java","lineNumber":63},{"declaringClass":"io.cucumber.core.runner.TestStep","methodName":"executeStep","fileName":"TestStep.java","lineNumber":92},{"declaringClass":"io.cucumber.core.runner.TestStep","methodName":"run","fileName":"TestStep.java","lineNumber":64},{"declaringClass":"io.cucumber.core.runner.PickleStepTestStep","methodName":"run","fileName":"PickleStepTestStep.java","lineNumber":51},{"declaringClass":"io.cucumber.core.runner.TestCase","methodName":"run","fileName":"TestCase.java","lineNumber":104},{"declaringClass":"io.cucumber.core.runner.Runner","methodName":"runPickle","fileName":"Runner.java","lineNumber":73},{"declaringClass":"io.cucumber.junit.FeatureRunner","methodName":"runChild","fileName":"FeatureRunner.java","lineNumber":135},{"declaringClass":"io.cucumber.junit.FeatureRunner","methodName":"runChild","fileName":"FeatureRunner.java","lineNumber":27},{"declaringClass":"io.cucumber.junit.CucumberSerenityRunner","methodName":"runChild","fileName":"CucumberSerenityRunner.java","lineNumber":258},{"declaringClass":"io.cucumber.junit.CucumberSerenityRunner","methodName":"runChild","fileName":"CucumberSerenityRunner.java","lineNumber":57},{"declaringClass":"worker.org.gradle.process.internal.worker.GradleWorkerMain","methodName":"run","fileName":"GradleWorkerMain.java","lineNumber":69},{"declaringClass":"worker.org.gradle.process.internal.worker.GradleWorkerMain","methodName":"main","fileName":"GradleWorkerMain.java","lineNumber":74}]}},"result":"FAILURE","precondition":false,"level":2}]}]},{"number":8,"description":"Then the user observes that the page is translated into Mandarin","duration":12,"startTime":"2023-09-28T08:37:53.422-05:00[America/Bogota]","result":"SKIPPED","precondition":false,"level":0}],"userStory":{"id":"change-page-language","storyName":"Change page language","path":"changelanguages.feature","narrative":"  As a web user, I change the language of the page","type":"feature"},"featureTag":{"name":"Change page language","type":"feature","displayName":"Change page language"},"title":"Validation of language change to \"Mandarin\"","description":"","tags":[{"name":"Change page language","type":"feature","displayName":"Change page language"}],"startTime":"2023-09-28T08:37:36.153-05:00[America/Bogota]","duration":17282,"testFailureCause":{"errorType":"net.thucydides.core.webdriver.exceptions.ElementShouldBePresentException","message":"Expected condition failed: waiting for By.xpath: //button [@data-testid \u003d \u0027selection-item\u0027]//span [contains(text(),\u0027简体中文\u0027)] to be present (tried for 5 second(s) with 100 milliseconds interval)\nBuild info: version: \u00273.141.59\u0027, revision: \u0027e82be7d358\u0027, time: \u00272018-11-14T08:17:03\u0027\nSystem info: host: \u0027DESKTOP-AM3VRUH\u0027, ip: \u0027172.18.1.223\u0027, os.name: \u0027Windows 10\u0027, os.arch: \u0027amd64\u0027, os.version: \u002710.0\u0027, java.version: \u00271.8.0_202\u0027\nDriver info: driver.version: unknown","stackTrace":[{"declaringClass":"com.co.booking.task.ChangeLanguageMandarin","methodName":"performAs","fileName":"ChangeLanguageMandarin.java","lineNumber":15},{"declaringClass":"com.co.booking.steptsdefinitions.changeLanguagesStepDefinition","methodName":"theUserChangesTheLanguageToMandarin","fileName":"changeLanguagesStepDefinition.java","lineNumber":138},{"declaringClass":"io.cucumber.java.Invoker","methodName":"doInvoke","fileName":"Invoker.java","lineNumber":66},{"declaringClass":"io.cucumber.java.Invoker","methodName":"invoke","fileName":"Invoker.java","lineNumber":24},{"declaringClass":"io.cucumber.java.AbstractGlueDefinition","methodName":"invokeMethod","fileName":"AbstractGlueDefinition.java","lineNumber":47},{"declaringClass":"io.cucumber.java.JavaStepDefinition","methodName":"execute","fileName":"JavaStepDefinition.java","lineNumber":29},{"declaringClass":"io.cucumber.core.runner.CoreStepDefinition","methodName":"execute","fileName":"CoreStepDefinition.java","lineNumber":66},{"declaringClass":"io.cucumber.core.runner.PickleStepDefinitionMatch","methodName":"runStep","fileName":"PickleStepDefinitionMatch.java","lineNumber":63},{"declaringClass":"io.cucumber.core.runner.TestStep","methodName":"executeStep","fileName":"TestStep.java","lineNumber":92},{"declaringClass":"io.cucumber.core.runner.TestStep","methodName":"run","fileName":"TestStep.java","lineNumber":64},{"declaringClass":"io.cucumber.core.runner.PickleStepTestStep","methodName":"run","fileName":"PickleStepTestStep.java","lineNumber":51},{"declaringClass":"io.cucumber.core.runner.TestCase","methodName":"run","fileName":"TestCase.java","lineNumber":104},{"declaringClass":"io.cucumber.core.runner.Runner","methodName":"runPickle","fileName":"Runner.java","lineNumber":73},{"declaringClass":"io.cucumber.junit.FeatureRunner","methodName":"runChild","fileName":"FeatureRunner.java","lineNumber":135},{"declaringClass":"io.cucumber.junit.FeatureRunner","methodName":"runChild","fileName":"FeatureRunner.java","lineNumber":27},{"declaringClass":"io.cucumber.junit.CucumberSerenityRunner","methodName":"runChild","fileName":"CucumberSerenityRunner.java","lineNumber":258},{"declaringClass":"io.cucumber.junit.CucumberSerenityRunner","methodName":"runChild","fileName":"CucumberSerenityRunner.java","lineNumber":57},{"declaringClass":"worker.org.gradle.process.internal.worker.GradleWorkerMain","methodName":"run","fileName":"GradleWorkerMain.java","lineNumber":69},{"declaringClass":"worker.org.gradle.process.internal.worker.GradleWorkerMain","methodName":"main","fileName":"GradleWorkerMain.java","lineNumber":74}],"rootCause":{"errorType":"org.openqa.selenium.TimeoutException","message":"Expected condition failed: waiting for By.xpath: //button [@data-testid \u003d \u0027selection-item\u0027]//span [contains(text(),\u0027简体中文\u0027)] to be present (tried for 5 second(s) with 100 milliseconds interval)\nBuild info: version: \u00273.141.59\u0027, revision: \u0027e82be7d358\u0027, time: \u00272018-11-14T08:17:03\u0027\nSystem info: host: \u0027DESKTOP-AM3VRUH\u0027, ip: \u0027172.18.1.223\u0027, os.name: \u0027Windows 10\u0027, os.arch: \u0027amd64\u0027, os.version: \u002710.0\u0027, java.version: \u00271.8.0_202\u0027\nDriver info: driver.version: unknown","stackTrace":[{"declaringClass":"com.co.booking.task.ChangeLanguageMandarin","methodName":"performAs","fileName":"ChangeLanguageMandarin.java","lineNumber":15},{"declaringClass":"com.co.booking.steptsdefinitions.changeLanguagesStepDefinition","methodName":"theUserChangesTheLanguageToMandarin","fileName":"changeLanguagesStepDefinition.java","lineNumber":138},{"declaringClass":"io.cucumber.java.Invoker","methodName":"doInvoke","fileName":"Invoker.java","lineNumber":66},{"declaringClass":"io.cucumber.java.Invoker","methodName":"invoke","fileName":"Invoker.java","lineNumber":24},{"declaringClass":"io.cucumber.java.AbstractGlueDefinition","methodName":"invokeMethod","fileName":"AbstractGlueDefinition.java","lineNumber":47},{"declaringClass":"io.cucumber.java.JavaStepDefinition","methodName":"execute","fileName":"JavaStepDefinition.java","lineNumber":29},{"declaringClass":"io.cucumber.core.runner.CoreStepDefinition","methodName":"execute","fileName":"CoreStepDefinition.java","lineNumber":66},{"declaringClass":"io.cucumber.core.runner.PickleStepDefinitionMatch","methodName":"runStep","fileName":"PickleStepDefinitionMatch.java","lineNumber":63},{"declaringClass":"io.cucumber.core.runner.TestStep","methodName":"executeStep","fileName":"TestStep.java","lineNumber":92},{"declaringClass":"io.cucumber.core.runner.TestStep","methodName":"run","fileName":"TestStep.java","lineNumber":64},{"declaringClass":"io.cucumber.core.runner.PickleStepTestStep","methodName":"run","fileName":"PickleStepTestStep.java","lineNumber":51},{"declaringClass":"io.cucumber.core.runner.TestCase","methodName":"run","fileName":"TestCase.java","lineNumber":104},{"declaringClass":"io.cucumber.core.runner.Runner","methodName":"runPickle","fileName":"Runner.java","lineNumber":73},{"declaringClass":"io.cucumber.junit.FeatureRunner","methodName":"runChild","fileName":"FeatureRunner.java","lineNumber":135},{"declaringClass":"io.cucumber.junit.FeatureRunner","methodName":"runChild","fileName":"FeatureRunner.java","lineNumber":27},{"declaringClass":"io.cucumber.junit.CucumberSerenityRunner","methodName":"runChild","fileName":"CucumberSerenityRunner.java","lineNumber":258},{"declaringClass":"io.cucumber.junit.CucumberSerenityRunner","methodName":"runChild","fileName":"CucumberSerenityRunner.java","lineNumber":57},{"declaringClass":"worker.org.gradle.process.internal.worker.GradleWorkerMain","methodName":"run","fileName":"GradleWorkerMain.java","lineNumber":69},{"declaringClass":"worker.org.gradle.process.internal.worker.GradleWorkerMain","methodName":"main","fileName":"GradleWorkerMain.java","lineNumber":74}]}},"testFailureClassname":"net.thucydides.core.webdriver.exceptions.ElementShouldBePresentException","testFailureMessage":"Expected condition failed: waiting for By.xpath: //button [@data-testid \u003d \u0027selection-item\u0027]//span [contains(text(),\u0027简体中文\u0027)] to be present (tried for 5 second(s) with 100 milliseconds interval)\nBuild info: version: \u00273.141.59\u0027, revision: \u0027e82be7d358\u0027, time: \u00272018-11-14T08:17:03\u0027\nSystem info: host: \u0027DESKTOP-AM3VRUH\u0027, ip: \u0027172.18.1.223\u0027, os.name: \u0027Windows 10\u0027, os.arch: \u0027amd64\u0027, os.version: \u002710.0\u0027, java.version: \u00271.8.0_202\u0027\nDriver info: driver.version: unknown","testFailureSummary":"FAILURE;net.thucydides.core.webdriver.exceptions.ElementShouldBePresentException;Expected condition failed: waiting for By.xpath: //button [@data-testid \u003d \u0027selection-item\u0027]//span [contains(text(),\u0027简体中文\u0027)] to be present (tried for 5 second(s) with 100 milliseconds interval)\nBuild info: version: \u00273.141.59\u0027, revision: \u0027e82be7d358\u0027, time: \u00272018-11-14T08:17:03\u0027\nSystem info: host: \u0027DESKTOP-AM3VRUH\u0027, ip: \u0027172.18.1.223\u0027, os.name: \u0027Windows 10\u0027, os.arch: \u0027amd64\u0027, os.version: \u002710.0\u0027, java.version: \u00271.8.0_202\u0027\nDriver info: driver.version: unknown;ChangeLanguageMandarin.java","projectKey":"","annotatedResult":"FAILURE","sessionId":"9ecbee6eb1d4aa1e35e58e3293c7a56e","driver":"chrome","isManualTestingUpToDate":false,"manual":false,"testSource":"Cucumber","actors":[{"name":"Team15","can":["browse the web"]}],"result":"FAILURE"}